j_formatter/__init__.py
j_formatter/j_formater.py
j_formatter-0.1.0.dist-info/LICENSE
j_formatter-0.1.0.dist-info/METADATA
j_formatter-0.1.0.dist-info/WHEEL
j_formatter-0.1.0.dist-info/top_level.txt
j_formatter-0.1.0.dist-info/RECORD
