Metadata-Version: 2.1
Name: j-formatter
Version: 0.1.0
Summary: Python Package to get the provided time in seconds to JIRA like format
Home-page: UNKNOWN
Author: AVS
Author-email: arjunvs.vs@gmail.com
License: UNKNOWN
Platform: UNKNOWN
License-File: LICENSE
